consoletetris-0.1.3.dist-info/METADATA
consoletetris-0.1.3.dist-info/RECORD
consoletetris-0.1.3.dist-info/WHEEL
consoletetris-0.1.3.dist-info/entry_points.txt
consoletetris-0.1.3.dist-info/top_level.txt
tetris/__init__.py
tetris/shapes.py
tetris/tetris.py
